[
  {
    "name": "Leather Belt",
    "description": "A belt made from leather and other light materials. Basic general equipment.",
    "type": "All",
    "gender": "Both",
    "rarity": 1,
    "slots": 0,
    "stats": {
      "defense": "1-71",
      "fire": -1,
      "water": 0,
      "ice": 0,
      "thunder": 0,
      "dragon": 1
    },
    "price": 50,
    "skills": {
      "Gathering": 3,
      "Fate": -1,
      "Health": 2,
      "Whim": 1
    },
    "materials": {
      "Warm Pelt": 1,
      "Monster Bone S": 1
    }
  },
  {
    "name": "Derring Belt",
    "description": "Waist armor tailored for the Caravan. Sturdy and designed to get the job done.",
    "type": "All",
    "gender": "Both",
    "rarity": 1,
    "slots": 2,
    "stats": {
      "defense": "1-71",
      "fire": 2,
      "water": 0,
      "ice": 0,
      "thunder": 0,
      "dragon": 1
    },
    "price": 50,
    "skills": {
      "Health": -2,
      "Rec Speed": 3,
      "Mounting": 1
    },
    "materials": {
      "Monster Bone S": 1,
      "Iron Ore": 1
    }
  },
  {
    "name": "Chainmail Belt",
    "description": "A simple belt, but crafted with a special process. Thin and light on the hips.",
    "type": "All",
    "gender": "Both",
    "rarity": 1,
    "slots": 0,
    "stats": {
      "defense": "4-73",
      "fire": 2,
      "water": 1,
      "ice": 1,
      "thunder": -2,
      "dragon": 0
    },
    "price": 400,
    "skills": {
      "Health": 2,
      "Hunger": 4
    },
    "materials": {
      "Iron Ore": 1,
      "Warm Pelt": 2
    }
  },
  {
    "name": "Hunter's Faulds",
    "description": "Waist armor made especially for hunters. Pliant yet durable, used by many hunters.",
    "type": "Blademaster",
    "gender": "Both",
    "rarity": 1,
    "slots": 1,
    "stats": {
      "defense": "6-112",
      "fire": 0,
      "water": 1,
      "ice": 0,
      "thunder": -3,
      "dragon": 0
    },
    "price": 750,
    "skills": {
      "Combo Rate": 2,
      "Ranger": 1,
      "Poison": -1
    },
    "materials": {
      "Machalite Ore": 2,
      "Iron Ore": 1,
      "Glueglopper": 1
    }
  },
  {
    "name": "Hunter's Coat",
    "description": "Waist armor made especially for hunters. Well designed, down to the finest details.",
    "type": "Gunner",
    "gender": "Both",
    "rarity": 1,
    "slots": 1,
    "stats": {
      "defense": "3-72",
      "fire": 1,
      "water": 2,
      "ice": 1,
      "thunder": -2,
      "dragon": 1
    },
    "price": 750,
    "skills": {
      "Combo Rate": 2,
      "Ranger": 1,
      "Poison": -1
    },
    "materials": {
      "Machalite Ore": 2,
      "Iron Ore": 1,
      "Glueglopper": 1
    }
  },
  {
    "name": "Bone Faulds",
    "description": "Waist armor adorned with monster bones. The spines on its rear are a key feature.",
    "type": "Blademaster",
    "gender": "Both",
    "rarity": 1,
    "slots": 1,
    "stats": {
      "defense": "7-113",
      "fire": 1,
      "water": 0,
      "ice": -2,
      "thunder": -1,
      "dragon": 0
    },
    "price": 800,
    "skills": {
      "KO": 2,
      "Maestro": 3
    },
    "materials": {
      "Mystery Bone": 2,
      "Monster Bone S": 2,
      "Sharp Fang": 2
    }
  },
  {
    "name": "Bone Coat",
    "description": "Waist armor crafted from monster bones. Skimpy, but surprisingly practical.",
    "type": "Gunner",
    "gender": "Both",
    "rarity": 1,
    "slots": 1,
    "stats": {
      "defense": "4-73",
      "fire": 2,
      "water": 1,
      "ice": -1,
      "thunder": 0,
      "dragon": 1
    },
    "price": 800,
    "skills": {
      "KO": 2,
      "Maestro": 3
    },
    "materials": {
      "Mystery Bone": 2,
      "Monster Bone S": 2,
      "Sharp Fang": 2
    }
  },
  {
    "name": "Alloy Coil",
    "description": "Waist armor made with quality Machalite Ore. Its sleek design has real beauty.",
    "type": "Blademaster",
    "gender": "Both",
    "rarity": 1,
    "slots": 0,
    "stats": {
      "defense": "8-114",
      "fire": -1,
      "water": 1,
      "ice": -1,
      "thunder": -2,
      "dragon": 0
    },
    "price": 850,
    "skills": {
      "Defense": 4,
      "Gathering": -1,
      "Wind Res": 1
    },
    "materials": {
      "Machalite Ore": 2,
      "Monster Bone S": 2,
      "Iron Ore": 3
    }
  },
  {
    "name": "Alloy Coat",
    "description": "Waist armor made with quality Machalite Ore. Its design exudes fine craftsmanship.",
    "type": "Gunner",
    "gender": "Both",
    "rarity": 1,
    "slots": 0,
    "stats": {
      "defense": "4-73",
      "fire": 0,
      "water": 2,
      "ice": 0,
      "thunder": -1,
      "dragon": 1
    },
    "price": 850,
    "skills": {
      "Gathering": -2,
      "Pellet Up": 3,
      "Pellet S+": 2
    },
    "materials": {
      "Machalite Ore": 2,
      "Monster Bone S": 2,
      "Iron Ore": 3
    }
  },
  {
    "name": "Loc Lac Kilt",
    "description": "Desert waist armor. Widely used for its reliable heat-resistant properties.",
    "type": "All",
    "gender": "Both",
    "rarity": 1,
    "slots": 2,
    "stats": {
      "defense": "5-73",
      "fire": 2,
      "water": -3,
      "ice": 0,
      "thunder": 1,
      "dragon": 0
    },
    "price": 900,
    "skills": {
      "Heat Res": 3,
      "Transportr": 4
    },
    "materials": {
      "Steel Egg": 1,
      "Altaroth Jaw": 1,
      "Sharp Fang": 3
    }
  },
  {
    "name": "Light Belt",
    "description": "Simple leather belt with unique crafting. Thin, thus lightly worn on the waist.",
    "type": "All",
    "gender": "Both",
    "rarity": 1,
    "slots": 1,
    "stats": {
      "defense": "5-73",
      "fire": -2,
      "water": 2,
      "ice": 2,
      "thunder": 2,
      "dragon": -2
    },
    "price": 900,
    "skills": {
      "Gathering": 4,
      "Transportr": 5
    },
    "materials": {
      "Slagtoth Hide": 5,
      "Altaroth Stomach": 3,
      "Paddock Oil": 3
    }
  },
  {
    "name": "Iron Belt",
    "description": "Waist armor strengthened with Iron Ore. Stronger than leather, it covers one's weak points.",
    "type": "All",
    "gender": "Both",
    "rarity": 1,
    "slots": 1,
    "stats": {
      "defense": "8-74",
      "fire": 4,
      "water": -4,
      "ice": -2,
      "thunder": -6,
      "dragon": 0
    },
    "price": 2150,
    "skills": {
      "Spd Gather": 10
    },
    "materials": {
      "Dragonite Ore": 2,
      "Warm Pelt": 3,
      "Konchu Shell": 5
    }
  },
  {
    "name": "Bnahabra Coil",
    "description": "Waist armor created for a fanciful aristocrat, who was fond of collecting curiosities.",
    "type": "Blademaster",
    "gender": "Both",
    "rarity": 2,
    "slots": 0,
    "stats": {
      "defense": "10-116",
      "fire": -4,
      "water": -1,
      "ice": -1,
      "thunder": 2,
      "dragon": 2
    },
    "price": 1400,
    "skills": {
      "Attack": -1,
      "Status": 1,
      "Sheathing": 2,
      "Paralysis": 4
    },
    "materials": {
      "Bnahabra Wing": 3,
      "Bnahabra Shell": 2,
      "Monster Fluid": 1,
      "Flashbug": 2
    }
  },
  {
    "name": "Rhenoplos Coil",
    "description": "Waist armor made from Rhenoplos parts. Ideal for desert water and ore prospecting.",
    "type": "Blademaster",
    "gender": "Both",
    "rarity": 2,
    "slots": 1,
    "stats": {
      "defense": "8-114",
      "fire": 1,
      "water": -1,
      "ice": -1,
      "thunder": -1,
      "dragon": 1
    },
    "price": 850,
    "skills": {
      "KO": 2,
      "Stun": -1,
      "Mud/Snow": 3
    },
    "materials": {
      "Rhenoplos Shell": 2,
      "Rhenoplos Scalp": 1,
      "Earth Crystal": 2
    }
  },
  {
    "name": "Rhenoplos Coat",
    "description": "Waist armor made from Rhenoplos parts, with wide coverage for the legs.",
    "type": "Gunner",
    "gender": "Both",
    "rarity": 2,
    "slots": 1,
    "stats": {
      "defense": "4-73",
      "fire": 2,
      "water": 0,
      "ice": 0,
      "thunder": 0,
      "dragon": 2
    },
    "price": 850,
    "skills": {
      "KO": 3,
      "Stun": -1,
      "Mud/Snow": 2
    },
    "materials": {
      "Rhenoplos Shell": 2,
      "Rhenoplos Scalp": 1,
      "Earth Crystal": 2
    }
  },
  {
    "name": "Remobra Belt",
    "description": "A belt fashioned from Remobra spoils. Nothing says 'attitude' like a skull.",
    "type": "Blademaster",
    "gender": "Both",
    "rarity": 2,
    "slots": 0,
    "stats": {
      "defense": "15-117",
      "fire": 1,
      "water": -2,
      "ice": 1,
      "thunder": 2,
      "dragon": -3
    },
    "price": 2000,
    "skills": {
      "Torso Up": 1
    },
    "materials": {
      "Remobra Hide": 4,
      "Monster Bone+": 1,
      "Monster Fluid": 3,
      "Vermin Coin": 1
    }
  },
  {
    "name": "Remobra Band",
    "description": "A unique belt fashioned from Remobra spoils. The design is in demand worldwide.",
    "type": "Gunner",
    "gender": "Both",
    "rarity": 2,
    "slots": 0,
    "stats": {
      "defense": "8-74",
      "fire": 2,
      "water": -1,
      "ice": 2,
      "thunder": 3,
      "dragon": -2
    },
    "price": 2000,
    "skills": {
    },
    "materials": {
      "Remobra Hide": 4,
      "Monster Bone+": 1,
      "Monster Fluid": 3,
      "Vermin Coin": 1
    }
  },
  {
    "name": "Jaggi Faulds",
    "description": "Waist armor made from Jaggi parts. A flamboyant use of the Jaggi's beautiful skin.",
    "type": "Blademaster",
    "gender": "Both",
    "rarity": 2,
    "slots": 0,
    "stats": {
      "defense": "10-116",
      "fire": -2,
      "water": 0,
      "ice": 0,
      "thunder": 0,
      "dragon": 1
    },
    "price": 950,
    "skills": {
      "Sharpener": 2,
      "LastingPwr": -1,
      "Stun": 3
    },
    "materials": {
      "G.Jaggi Hide": 2,
      "King's Frill": 1,
      "Jaggi Hide": 3,
      "Earth Crystal": 1
    }
  },
  {
    "name": "Jaggi Coat",
    "description": "Waist armor made from Jaggi parts. The striking pattern is rather eye-catching.",
    "type": "Gunner",
    "gender": "Both",
    "rarity": 2,
    "slots": 0,
    "stats": {
      "defense": "5-73",
      "fire": -1,
      "water": 1,
      "ice": 1,
      "thunder": 1,
      "dragon": 2
    },
    "price": 950,
    "skills": {
      "Reload Spd": 2,
      "LastingPwr": -1,
      "Stun": 2
    },
    "materials": {
      "G.Jaggi Hide": 2,
      "King's Frill": 1,
      "Jaggi Hide": 3,
      "Earth Crystal": 1
    }
  },
  {
    "name": "Genprey Tassets",
    "description": "Waist armor made from Genprey materials. Sister to the Velociprey Tassets.",
    "type": "Blademaster",
    "gender": "Both",
    "rarity": 2,
    "slots": 1,
    "stats": {
      "defense": "12-116",
      "fire": 1,
      "water": 1,
      "ice": -3,
      "thunder": -2,
      "dragon": 2
    },
    "price": 1050,
    "skills": {
      "Rec Speed": -2,
      "Paralysis": 5
    },
    "materials": {
      "Genprey Hide": 4,
      "Genprey Scale": 3,
      "Iron Ore": 2
    }
  },
  {
    "name": "Genprey Coat",
    "description": "Armor made from a combination of ore and Genprey parts. Has been extremely finely crafted.",
    "type": "Gunner",
    "gender": "Both",
    "rarity": 2,
    "slots": 1,
    "stats": {
      "defense": "6-73",
      "fire": 2,
      "water": 2,
      "ice": -2,
      "thunder": -1,
      "dragon": 3
    },
    "price": 1050,
    "skills": {
      "Rec Speed": -2,
      "Paralysis": 5
    },
    "materials": {
      "Genprey Hide": 4,
      "Genprey Scale": 3,
      "Iron Ore": 2
    }
  },
  {
    "name": "Ioprey Tassets",
    "description": "Waist armor made from Ioprey parts. Top of the line 'Prey armor for ultimate protection.",
    "type": "Blademaster",
    "gender": "Both",
    "rarity": 2,
    "slots": 1,
    "stats": {
      "defense": "15-117",
      "fire": 0,
      "water": -3,
      "ice": 2,
      "thunder": -3,
      "dragon": 2
    },
    "price": 1850,
    "skills": {
      "Status": 1,
      "Poison": 5,
      "Stun": -2
    },
    "materials": {
      "Iodrome Hide": 2,
      "Monster Bone M": 3,
      "Ioprey Scale": 2,
      "Machalite Ore": 3
    }
  },
  {
    "name": "Ioprey Coat",
    "description": "Beautiful armor made from red scales. Expertly crafted from Ioprey parts and ore.",
    "type": "Gunner",
    "gender": "Both",
    "rarity": 2,
    "slots": 2,
    "stats": {
      "defense": "8-74",
      "fire": 1,
      "water": -2,
      "ice": 3,
      "thunder": -2,
      "dragon": 3
    },
    "price": 1850,
    "skills": {
      "Status": 1,
      "Poison": 4,
      "Stun": -2
    },
    "materials": {
      "Iodrome Hide": 2,
      "Monster Bone M": 3,
      "Ioprey Scale": 2,
      "Machalite Ore": 3
    }
  },
  {
    "name": "Lagombi Faulds",
    "description": "Unique waist armor designed for everyday use for those who live in freezing climes.",
    "type": "Blademaster",
    "gender": "Both",
    "rarity": 2,
    "slots": 1,
    "stats": {
      "defense": "15-117",
      "fire": -2,
      "water": 2,
      "ice": 2,
      "thunder": -1,
      "dragon": 2
    },
    "price": 2150,
    "skills": {
      "Evade Dist": 2,
      "Heat Res": -1,
      "Cold Res": 2
    },
    "materials": {
      "Lagombi Pelt": 3,
      "Lagombi Iceclaw": 1,
      "Jumbo Bone": 2,
      "Killer Beetle": 3
    }
  },
  {
    "name": "Lagombi Coat",
    "description": "Waist armor used in frigid regions. Known and trusted for its use as hunting equipment.",
    "type": "Gunner",
    "gender": "Both",
    "rarity": 2,
    "slots": 1,
    "stats": {
      "defense": "8-74",
      "fire": -1,
      "water": 3,
      "ice": 3,
      "thunder": 0,
      "dragon": 3
    },
    "price": 2150,
    "skills": {
      "Evade Dist": 2,
      "Heat Res": -1,
      "Cold Res": 2
    },
    "materials": {
      "Lagombi Pelt": 3,
      "Lagombi Iceclaw": 1,
      "Jumbo Bone": 2,
      "Killer Beetle": 3
    }
  },
  {
    "name": "Kecha Faulds",
    "description": "Waist armor with a regional Kecha Wacha ear motif said to bring luck to the hunt.",
    "type": "Blademaster",
    "gender": "Both",
    "rarity": 2,
    "slots": 1,
    "stats": {
      "defense": "14-116",
      "fire": -3,
      "water": 2,
      "ice": 0,
      "thunder": -2,
      "dragon": 2
    },
    "price": 1150,
    "skills": {
      "Fate": -2,
      "Water Atk": 2,
      "Whim": 2
    },
    "materials": {
      "Kecha Longbone": 2,
      "Kecha Ear": 1,
      "Monster Bone S": 2,
      "Ivy": 3
    }
  },
  {
    "name": "Kecha Coat",
    "description": "Waist armor with distinct ears. Light and handy, but also a folk art masterpiece.",
    "type": "Gunner",
    "gender": "Both",
    "rarity": 2,
    "slots": 1,
    "stats": {
      "defense": "7-74",
      "fire": -2,
      "water": 3,
      "ice": 1,
      "thunder": -1,
      "dragon": 3
    },
    "price": 1150,
    "skills": {
      "Fate": -2,
      "Water Atk": 2,
      "Whim": 2
    },
    "materials": {
      "Kecha Longbone": 2,
      "Kecha Ear": 1,
      "Monster Bone S": 2,
      "Ivy": 3
    }
  }
]
